propertize/__init__.py
propertize/propertize.py
propertize-0.0.3.dist-info/LICENSE
propertize-0.0.3.dist-info/METADATA
propertize-0.0.3.dist-info/WHEEL
propertize-0.0.3.dist-info/top_level.txt
propertize-0.0.3.dist-info/RECORD
