Metadata-Version: 2.1
Name: propertize
Version: 0.0.3
Summary: Unwrap custom properties
Home-page: https://github.com/jnawk/propertize
Author: Philip Dowie
Author-email: philip@jnawk.nz
License: MIT
Classifier: Environment :: Web Environment
Classifier: Intended Audience :: Developers
Classifier: License :: OSI Approved :: MIT License
Classifier: Operating System :: OS Independent
Classifier: Programming Language :: Python
Classifier: Topic :: Internet :: WWW/HTTP :: Dynamic Content
Classifier: Topic :: Software Development :: Libraries :: Python Modules
License-File: LICENSE
